[
    {
        "term": "bitbloq-faq-title-1",
        "definition": "O que \u00e9 o Bitbloq?",
        "context": "",
        "term_plural": "",
        "reference": "",
        "comment": ""
    },
    {
        "term": "bitbloq-faq-content-1",
        "definition": "O Bitbloq \u00e9 uma ferramenta online que permite criar programas para um microcontrolador e carreg\u00e1-os no mesmo, de forma simples e sem ter necessariamente conhecimentos de programa\u00e7\u00e3o.",
        "context": "",
        "term_plural": "",
        "reference": "",
        "comment": ""
    },
    {
        "term": "bitbloq-faq-title-2",
        "definition": "Como funciona o Bitbloq?",
        "context": "",
        "term_plural": "",
        "reference": "",
        "comment": ""
    },
    {
        "term": "bitbloq-faq-content-2",
        "definition": "Com o Bitbloq, programar\u00e1s por blocos de forma r\u00e1pida e intuitiva. Al\u00e9m disso, poder\u00e1s criar os teus pr\u00f3prios projetos e partilh\u00e1-los com a comunidade. A eletr\u00f3nica e a programa\u00e7\u00e3o nunca foram t\u00e3o divertidas!",
        "context": "",
        "term_plural": "",
        "reference": "",
        "comment": ""
    },
    {
        "term": "bitbloq-faq-title-3",
        "definition": "O que posso fazer no Bitbloq?",
        "context": "",
        "term_plural": "",
        "reference": "",
        "comment": ""
    },
    {
        "term": "bitbloq-faq-content-3",
        "definition": "Com o Bitbloq e a eletr\u00f3nica da BQ, poder\u00e1s criar tudo aquilo que imaginares, desde robots at\u00e9 projetos de dom\u00f3tica para casa, passando por jogos eletr\u00f3nicos. A tua imagina\u00e7\u00e3o n\u00e3o ter\u00e1 limites!",
        "context": "",
        "term_plural": "",
        "reference": "",
        "comment": ""
    },
    {
        "term": "bitbloq-faq-title-4",
        "definition": "Quem est\u00e1 por tr\u00e1s do projeto?",
        "context": "",
        "term_plural": "",
        "reference": "",
        "comment": ""
    },
    {
        "term": "bitbloq-faq-content-4",
        "definition": "Este projeto foi concebido desenvolvido pela BQ. Podes aqui ver a grande equipa que faz com que este projeto esteja dispon\u00edvel.",
        "context": "",
        "term_plural": "",
        "reference": "",
        "comment": ""
    },
    {
        "term": "bitbloq-faq-title-5",
        "definition": "A quem se destina?",
        "context": "",
        "term_plural": "",
        "reference": "",
        "comment": ""
    },
    {
        "term": "bitbloq-faq-content-5",
        "definition": "O Bitbloq d\u00e1 aos pais que queiram iniciar os seus filhos, na rob\u00f3tica, eletr\u00f3nica ou programa\u00e7\u00e3o, as ferramentas necess\u00e1rias para entrarem neste mundo apaixonante. Aos professores que queiram ensinar \u00e0s crian\u00e7as a serem criadores de tecnologia. \u00c0s crian\u00e7as que queiram aprender como funciona la tecnologia e queiram criar a sua pr\u00f3pria sem qualquer limite.",
        "context": "",
        "term_plural": "",
        "reference": "",
        "comment": ""
    },
    {
        "term": "bitbloq-faq-title-6",
        "definition": "Que placas s\u00e3o suportadas?",
        "context": "",
        "term_plural": "",
        "reference": "",
        "comment": ""
    },
    {
        "term": "bitbloq-faq-content-6",
        "definition": "Atualmente suportamos as placas Freaduino UNO, Arduino UNO e BQ Zum, mas iremos em breve adicionar mais, muitas mais!",
        "context": "",
        "term_plural": "",
        "reference": "",
        "comment": ""
    },
    {
        "term": "bitbloq-faq-title-7",
        "definition": "Onde est\u00e3o os projetos que tinha o antigo Bitbloq?",
        "context": "",
        "term_plural": "",
        "reference": "",
        "comment": ""
    },
    {
        "term": "bitbloq-faq-content-7",
        "definition": "Os projetos do antigo Bitbloq n\u00e3o s\u00e3o compat\u00edveis com a nova ferramenta, por isso n\u00e3o foi poss\u00edvel fazer a transfer\u00eancia. Ter\u00e1s de voltar a criar esses projetos na nova ferramenta. Pedimos desculpa pelo inconveniente.",
        "context": "",
        "term_plural": "",
        "reference": "",
        "comment": ""
    },
    {
        "term": "bitbloq-faq-title-8",
        "definition": "Bitbloq e Scratch",
        "context": "",
        "term_plural": "",
        "reference": "",
        "comment": ""
    },
    {
        "term": "bitbloq-faq-content-8",
        "definition": "O Bitbloq utiliza o mesmo paradigma de programa\u00e7\u00e3o que Scratch, ou seja, utiliza blocos que encaixam uns nos outros como se fosse um puzzle para construir programas. Isto permite que a programa\u00e7\u00e3o seja acess\u00edvel para as crian\u00e7as, porque n\u00e3o t\u00eam de se preocupar com a sintaxe (n\u00e3o precisam de aprender a escrever c\u00f3digo numa linguagem de programa\u00e7\u00e3o literal como Processing, C++ ou Java). O Bitbloq utiliza este paradigma porque a sua efici\u00eancia est\u00e1 demostrada junto das crian\u00e7as e porque, al\u00e9m disso, o Scratch j\u00e1 \u00e9 utilizado em muitas escolas e centros educativos. A nossa filosofia \u00e9 que \u00e9 melhor juntar for\u00e7as do que reinventar a roda. Desenvolvemos o Bitbloq utilizando bibliotecas de software com licen\u00e7a livre, fundamentalmente a bloqs, uma biblioteca desenvolvida pela BQ para a cria\u00e7\u00e3o de aplica\u00e7\u00f5es online baseadas em blocos.",
        "context": "",
        "term_plural": "",
        "reference": "",
        "comment": ""
    },
    {
        "term": "bitbloq-faq-title-9",
        "definition": "\u00c9 poss\u00edvel fazer videojogos com o Bitbloq?",
        "context": "",
        "term_plural": "",
        "reference": "",
        "comment": ""
    },
    {
        "term": "bitbloq-faq-content-9",
        "definition": "N\u00e3o \u00e9 poss\u00edvel fazer videojogos no computador, mas sim jogos utilizando a eletr\u00f3nica do Mi Primer Kit de Rob\u00f3tica ou qualquer outra eletr\u00f3nica que utilize a placa ZUM ou uma placa compat\u00edvel com Arduino. O Scratch foi concebido para ensinar \u00e0s crian\u00e7as a programar realizando videojogos, enquanto o Bitbloq foi concebido para ensinar \u00e0s crian\u00e7as a programar utilizando eletr\u00f3nica e realizando projetos rob\u00f3ticos, dom\u00f3tica, inven\u00e7\u00f5es caseiras, etc.",
        "context": "",
        "term_plural": "",
        "reference": "",
        "comment": ""
    },
    {
        "term": "bitbloq-faq-title-10",
        "definition": "Pol\u00edtica de privacidade",
        "context": "",
        "term_plural": "",
        "reference": "",
        "comment": ""
    },
    {
        "term": "bitbloq-faq-content-10",
        "definition": "Os dados de car\u00e1ter pessoal proporcionados far\u00e3o parte de um ficheiro cujo respons\u00e1vel \u00e9 a Mundo Reader, S.L., sendo este gerido em conformidade com a regulamenta\u00e7\u00e3o espanhola de prote\u00e7\u00e3o de dados, com a finalidade de prestar este servi\u00e7o aos utilizadores de acordo com as condi\u00e7\u00f5es gerais em vigor. Consulta a nossa pol\u00edtica de privacidade em www.bq.com. Ao criar uma conta, o utilizador reconhece ter lido e aceite as condi\u00e7\u00f5es da pol\u00edtica de privacidade. Se tiveres qualquer d\u00favida em rela\u00e7\u00e3o \u00e0 pol\u00edtica ou ao tratamento que fazemos dos seus dados pessoais, contacta com lopd@bq.com.",
        "context": "",
        "term_plural": "",
        "reference": "",
        "comment": ""
    },
    {
        "term": "bitbloq-faq-title-11",
        "definition": "O Web2Board n\u00e3o pode ser aberto no Windows",
        "context": "",
        "term_plural": "",
        "reference": "",
        "comment": ""
    },
    {
        "term": "bitbloq-faq-content-11",
        "definition": "Reinstala o Web2Board como administrador. Para isso, clica direito no execut\u00e1vel e seleciona \"Executar como administrador\".",
        "context": "",
        "term_plural": "",
        "reference": "",
        "comment": ""
    },
    {
        "term": "bitbloq-faq-title-12",
        "definition": "No posso iniciar sess\u00e3o no Bitbloq",
        "context": "",
        "term_plural": "",
        "reference": "",
        "comment": ""
    },
    {
        "term": "bitbloq-faq-content-12",
        "definition": "Verifica se a data e hora do teu computador est\u00e3o corretas. Se n\u00e3o for o caso, corrige-as e tenta novamente.",
        "context": "",
        "term_plural": "",
        "reference": "",
        "comment": ""
    },
    {
        "term": "bitbloq-faq-title-13",
        "definition": "Os blocos soltos n\u00e3o geram c\u00f3digo",
        "context": "",
        "term_plural": "",
        "reference": "",
        "comment": ""
    },
    {
        "term": "bitbloq-faq-content-13",
        "definition": "A nova estrutura de programa\u00e7\u00e3o do Bitbloq 2 est\u00e1 pensada de tal forma que \u00e9 preciso conectar os blocos a algum bloco de projeto (\"Vari\u00e1veis globais e fun\u00e7\u00f5es\", \"Instru\u00e7\u00f5es iniciais (Setup)\" ou \"Circuito principal (Loop)\"). Qualquer bloco n\u00e3o conectado n\u00e3o gera c\u00f3digo e portanto n\u00e3o se ver\u00e1s o seu efeito na placa ou robot.",
        "context": "",
        "term_plural": "",
        "reference": "",
        "comment": ""
    },
    {
        "term": "bitbloq-faq-title-14",
        "definition": "Os blocos que est\u00e3o soltos desapareceram do meu projeto",
        "context": "",
        "term_plural": "",
        "reference": "",
        "comment": ""
    },
    {
        "term": "bitbloq-faq-content-14",
        "definition": "A nova estrutura de programa\u00e7\u00e3o do Bitbloq 2 est\u00e1 pensada de tal forma que \u00e9 preciso conectar os blocos a algum bloco de projeto (\"Vari\u00e1veis globais e fun\u00e7\u00f5es\", \"Instru\u00e7\u00f5es iniciais (Setup)\" ou \"Circuito principal (Loop)\"). Qualquer bloco n\u00e3o conectado n\u00e3o ser\u00e1 guardado no projeto.",
        "context": "",
        "term_plural": "",
        "reference": "",
        "comment": ""
    },
    {
        "term": "bitbloq-faq-title-15",
        "definition": "Porque \u00e9 que as crian\u00e7as de menos de 14 anos n\u00e3o se podem criar uma conta?",
        "context": "",
        "term_plural": "",
        "reference": "",
        "comment": ""
    },
    {
        "term": "bitbloq-faq-content-15",
        "definition": "Devido \u00e0 lei org\u00e2nica de prote\u00e7\u00e3o de dados de car\u00e1ter pessoal, para que um menor de 14 anos pudesse criar uma conta, dev\u00edamos ter a autoriza\u00e7\u00e3o expl\u00edcita do pai\/m\u00e3e\/tutor, e estes nos fornecerem uma extensa documenta\u00e7\u00e3o. Por essa raz\u00e3o, n\u00e3o podemos permitir que criem contas de utilizador mas apenas que utilizem contas de utilizadores criadas por pessoas de mais de 14 anos e utilizar o Bitbloq acompanhados dessa pessoa.",
        "context": "",
        "term_plural": "",
        "reference": "",
        "comment": ""
    },
    {
        "term": "bitbloq-faq-title-16",
        "definition": "N\u00e3o deteta a minha placa",
        "context": "",
        "term_plural": "",
        "reference": "",
        "comment": ""
    },
    {
        "term": "bitbloq-faq-content-16",
        "definition": "Podem existir diferentes problemas que expliquem a n\u00e3o dete\u00e7\u00e3o da placa. Apresentamos alguns a seguir. Experimenta e se o problema persistir, envia-nos uma mensagem\n1.- Se a placa for uma zum, verifica se o interruptor est\u00e1 em \"ON\"\n2.- Desconecta todos os componentes conectados e tenta carregar novamente o programa\n3.- Desconecta o usb da placa e volte a conect\u00e1-la\n4.- Carrega no bot\u00e3o de reset da placa e clica ao mesmo tempo em \"carregar\". Solta-o imediatamente antes de come\u00e7ares a programar a placa",
        "context": "",
        "term_plural": "",
        "reference": "",
        "comment": ""
    },
    {
        "term": "bitbloq-faq-title-17",
        "definition": "Na bq ZUM, o LCD n\u00e3o acende",
        "context": "",
        "term_plural": "",
        "reference": "",
        "comment": ""
    },
    {
        "term": "bitbloq-faq-content-17",
        "definition": "Verifica que o bot\u00e3o on\/off da placa est\u00e1 conectado, no caso contr\u00e1rio, os componentes simples funcionam, mas os componentes que precisam de mais pot\u00eancia n\u00e3o.",
        "context": "",
        "term_plural": "",
        "reference": "",
        "comment": ""
    },
    {
        "term": "bitbloq-faq-title-18",
        "definition": "N\u00e3o consigo aceder atrav\u00e9s de Google plus com Chrome",
        "context": "",
        "term_plural": "",
        "reference": "",
        "comment": ""
    },
    {
        "term": "bitbloq-faq-content-18",
        "definition": "Atualiza o Chrome para a \u00faltima vers\u00e3o, uma vez que tem atualiza\u00e7\u00f5es pendentes, \u00e9 poss\u00edvel que n\u00e3o te deixe aceder.",
        "context": "",
        "term_plural": "",
        "reference": "",
        "comment": ""
    },
    {
        "term": "bitbloq-faq-title-19",
        "definition": "Como conectar o LCD \u00e0 placa?",
        "context": "",
        "term_plural": "",
        "reference": "",
        "comment": ""
    },
    {
        "term": "bitbloq-faq-content-19",
        "definition": "Conecta o cabo de SCL ao pino \"S\" anal\u00f3gico indicado no Bitbloq (numa bq ZUM, seria conect\u00e1-lo ao pino azul A5), a seguir, o cabo SDA no pino \"S\" anal\u00f3gico indicado no Bitbloq (numa bq ZUM, seria no pino azul A4).\\No pino VCC \u00e9 poss\u00edvel conectar qualquer pino anal\u00f3gico \"V\" e o pino GND pode ser conectado a qualquer pino anal\u00f3gico \"G\".",
        "context": "",
        "term_plural": "",
        "reference": "",
        "comment": ""
    },
    {
        "term": "bitbloq-faq-title-20",
        "definition": "Aparecem car\u00e1teres estranhos na placa LCD",
        "context": "",
        "term_plural": "",
        "reference": "",
        "comment": ""
    },
    {
        "term": "bitbloq-faq-content-20",
        "definition": "Existem duas causas poss\u00edveis pela quais podem aparecer car\u00e1teres estranhos no LCD em vez dos que foram programados:\n1.- O LCD n\u00e3o aceita a escrita de certos car\u00e1teres especiais tais como \u201c\u00a1\u201d, \u201c\u00bf\u201d ou \u201c\u00f1\u201d ou car\u00e1teres acentuados. Se forem usados, aparecem car\u00e1teres estranhos.\n2.- Verifica que o interruptor da parte traseira do LCD est\u00e1 em \"IIC\". Se n\u00e3o for o caso, aparecem car\u00e1teres estranhos.",
        "context": "",
        "term_plural": "",
        "reference": "",
        "comment": ""
    }
]